README.rst
setup.py
pycvss/__init__.py
pycvss/pycvss.py
pycvss.egg-info/PKG-INFO
pycvss.egg-info/SOURCES.txt
pycvss.egg-info/dependency_links.txt
pycvss.egg-info/top_level.txt
pycvss/test/__init__.py
pycvss/test/test_pycvss.py