Metadata-Version: 1.1
Name: pycvss
Version: 1.0.2
Summary: Cvss manipulation library to easily compute scores.
Home-page: https://github.com/attwad/pycvss
Author: attwad
Author-email: tmusoft@gmail.com
License: UNKNOWN
Platform: any
Classifier: Development Status :: 5 - Production/Stable
Classifier: Intended Audience :: Developers
Classifier: Programming Language :: Python :: 3
Classifier: Topic :: Security
Classifier: Topic :: Software Development :: Libraries
